applistenports/__init__.py
zabbix_app_ports_discovery-2019.2.22.4.dist-info/LICENSE
zabbix_app_ports_discovery-2019.2.22.4.dist-info/METADATA
zabbix_app_ports_discovery-2019.2.22.4.dist-info/WHEEL
zabbix_app_ports_discovery-2019.2.22.4.dist-info/top_level.txt
zabbix_app_ports_discovery-2019.2.22.4.dist-info/RECORD
